aiologstash/__init__.py
aiologstash/base_handler.py
aiologstash/log.py
aiologstash/py.typed
aiologstash/tcp_handler.py
aiologstash-2.0.0.dist-info/LICENSE
aiologstash-2.0.0.dist-info/WHEEL
aiologstash-2.0.0.dist-info/METADATA
aiologstash-2.0.0.dist-info/RECORD
