Metadata-Version: 2.1
Name: aiologstash
Version: 2.0.0
Summary: asyncio-compatible logstash logging handler.
Home-page: https://github.com/aio-libs/aiologstash
License: UNKNOWN
Author: Andrew Svetlov
Author-email: andrew.svetlov@gmail.com
Requires-Python: >=3.6.0
Classifier: Intended Audience :: Developers
Classifier: License :: OSI Approved :: MIT License
Classifier: Programming Language :: Python :: 3
Classifier: Programming Language :: Python :: 3.6
Classifier: Programming Language :: Python :: 3.7
Classifier: Programming Language :: Python :: 3.8
Classifier: Topic :: Software Development :: Libraries :: Python Modules
Classifier: Development Status :: 4 - Beta
Classifier: Framework :: AsyncIO
Requires-Dist: python-logstash
Requires-Dist: async-timeout
